stockfish_mcp/__main__.py
stockfish_mcp/chess_logic.py
stockfish_mcp/mcp_server.py
stockfish_mcp-1.0.2.dist-info/METADATA
stockfish_mcp-1.0.2.dist-info/WHEEL
stockfish_mcp-1.0.2.dist-info/entry_points.txt
stockfish_mcp-1.0.2.dist-info/top_level.txt
stockfish_mcp-1.0.2.dist-info/RECORD
