Metadata-Version: 2.4
Name: stockfish-mcp
Version: 1.0.2
Summary: A Stockfish MCP server
Author-email: Stephan Botes <stephanbotes@gmail.com>
Classifier: Programming Language :: Python :: 3
Classifier: License :: OSI Approved :: MIT License
Classifier: Operating System :: OS Independent
Requires-Python: >=3.8
Requires-Dist: fastmcp
Requires-Dist: chess
Requires-Dist: stockfish
